setup.py
django_fuse/__init__.py
django_fuse/fs.py
django_fuse/models.py
django_fuse/utils.py
django_fuse/views.py
django_fuse.egg-info/PKG-INFO
django_fuse.egg-info/SOURCES.txt
django_fuse.egg-info/dependency_links.txt
django_fuse.egg-info/requires.txt
django_fuse.egg-info/top_level.txt
django_fuse/management/__init__.py
django_fuse/management/commands/__init__.py
django_fuse/management/commands/mount.py
django_fuse_example/__init__.py
django_fuse_example/manage.py
django_fuse_example/settings.py
django_fuse_example/urls.py
django_fuse_example/example/__init__.py
django_fuse_example/example/models.py
django_fuse_example/example/urls.py
django_fuse_example/example/views.py