Metadata-Version: 1.0
Name: django-fuse
Version: 2.0.2
Summary: Abstractions for building FUSE filesystems using Django
Home-page: https://chris-lamb.co.uk/projects/django-fuse
Author: Chris Lamb
Author-email: chris@chris-lamb.co.uk
License: BSD
Platform: UNKNOWN
